polyconv/__init__.py
polyconv/__main__.py
polyconv/cli/__init__.py
polyconv/cli/main.py
polyconv/test_data/__init__.py
polyconv/test_data/test_data.py
polygon_convert-0.1.1.dist-info/licenses/LICENSE
polygon_convert-0.1.1.dist-info/METADATA
polygon_convert-0.1.1.dist-info/WHEEL
polygon_convert-0.1.1.dist-info/entry_points.txt
polygon_convert-0.1.1.dist-info/top_level.txt
polygon_convert-0.1.1.dist-info/RECORD
