Metadata-Version: 2.4
Name: polygon-convert
Version: 0.1.1
Summary: Convert Polygon packages to other formats, notably to CMS.
Author-email: Evirir <gojunxing@gmail.com>
License-Expression: GPL-3.0-or-later
Project-URL: Homepage, https://github.com/Evirir/polygon-convert
Project-URL: Issues, https://github.com/Evirir/polygon-convert/issues
Classifier: Programming Language :: Python :: 3
Classifier: Operating System :: OS Independent
Requires-Python: >=3.13
License-File: LICENSE
Dynamic: license-file
